BuiltInFunction/__init__.py
BuiltInFunction/core.py
builtinfunction-0.1.0.dist-info/METADATA
builtinfunction-0.1.0.dist-info/WHEEL
builtinfunction-0.1.0.dist-info/top_level.txt
builtinfunction-0.1.0.dist-info/RECORD
