Metadata-Version: 2.4
Name: BuiltInFunction
Version: 0.1.0
Summary: Custom built-in-like function
Author: Shahbaz
Requires-Python: >=3.6
Dynamic: author
Dynamic: requires-python
Dynamic: summary
